IPythonDisplayTurtle/__init__.py
IPythonDisplayTurtle/jspart/AtahansTurtle.js
IPythonDisplayTurtle/jspart/paper.js
IPythonDisplayTurtle-0.0.33.dist-info/LICENSE
IPythonDisplayTurtle-0.0.33.dist-info/METADATA
IPythonDisplayTurtle-0.0.33.dist-info/WHEEL
IPythonDisplayTurtle-0.0.33.dist-info/top_level.txt
IPythonDisplayTurtle-0.0.33.dist-info/RECORD
